{"verses":6604,"chapters":239,"slug":"bm","subtitle":"Another Testament of Jesus Christ","title_long":"The Book of Mormon","title":"Book of Mormon","books":[{"title":"1 Nephi","title_long":"The First Book of Nephi","title_short":"1 Ne.","slug":"1_ne","chapters":22,"verses":618},{"title":"2 Nephi","title_long":"The Second Book of Nephi","title_short":"2 Ne.","slug":"2_ne","chapters":33,"verses":779},{"title":"Jacob","title_long":"The Book of Jacob","title_short":"Jacob","slug":"jacob","chapters":7,"verses":203},{"title":"Enos","title_long":"The Book of Enos","title_short":"Enos","slug":"enos","chapters":1,"verses":27},{"title":"Jarom","title_long":"The Book of Jarom","title_short":"Jarom","slug":"jarom","chapters":1,"verses":15},{"title":"Omni","title_long":"The Book of Omni","title_short":"Omni","slug":"omni","chapters":1,"verses":30},{"title":"Words of Mormon","title_long":"Words of Mormon","title_short":"W of M","slug":"w_of_m","chapters":1,"verses":18},{"title":"Mosiah","title_long":"The Book of Mosiah","title_short":"Mosiah","slug":"mosiah","chapters":29,"verses":785},{"title":"Alma","title_long":"The Book of Alma","title_short":"Alma","slug":"alma","chapters":63,"verses":1975},{"title":"Helaman","title_long":"The Book of Helaman","title_short":"Hel.","slug":"hel","chapters":16,"verses":497},{"title":"3 Nephi","title_long":"The Third Book of Nephi","title_short":"3 Ne.","slug":"3_ne","chapters":30,"verses":785},{"title":"4 Nephi","title_long":"The Fourth Book of Nephi","title_short":"4 Ne.","slug":"4_ne","chapters":1,"verses":49},{"title":"Mormon","title_long":"The Book of Mormon","title_short":"Morm.","slug":"morm","chapters":9,"verses":227},{"title":"Ether","title_long":"The Book of Ether","title_short":"Ether","slug":"ether","chapters":15,"verses":433},{"title":"Moroni","title_long":"The Book of Moroni","title_short":"Moro.","slug":"moro","chapters":10,"verses":163}]}